{"stats":{"minecraft:used":{"atrox:spookyframe":29,"atrox:spookydimension":3,"atrox:spookyrack":2,"minecraft:stone_pressure_plate":1,"minecraft:enchanted_golden_apple":1,"atrox:trappedstonepressureplate":5},"minecraft:custom":{"minecraft:time_since_rest":5566,"minecraft:crouch_one_cm":410,"minecraft:walk_one_cm":11460,"minecraft:play_time":6628,"minecraft:sprint_one_cm":14984,"minecraft:damage_taken":650,"minecraft:deaths":1,"minecraft:damage_absorbed":159,"minecraft:sneak_time":489,"minecraft:jump":112,"minecraft:time_since_death":5507,"minecraft:climb_one_cm":185,"minecraft:total_world_time":6635,"minecraft:damage_resisted":434,"minecraft:fly_one_cm":143330},"minecraft:picked_up":{"minecraft:stone_bricks":3,"atrox:trappedstonepressureplate":5,"atrox:spookydimension":1,"minecraft:cracked_stone_bricks":2,"atrox:spookyframe":1,"minecraft:stone_brick_stairs":1,"atrox:spookstone_dust":44,"minecraft:mossy_stone_bricks":2,"minecraft:mossy_stone_brick_stairs":2,"minecraft:stone_pressure_plate":6}},"DataVersion":3465}